BayesianNetwork/BayesianNetwork.py
BayesianNetwork/__init__.py
BayesianNetwork-0.0.6.dist-info/METADATA
BayesianNetwork-0.0.6.dist-info/WHEEL
BayesianNetwork-0.0.6.dist-info/top_level.txt
BayesianNetwork-0.0.6.dist-info/RECORD
