Metadata-Version: 2.1
Name: BayesianNetwork
Version: 0.0.6
Summary: Librería simple para crear y resolver redes bayesianas
Home-page: 
Author: Christopher Garcia y Gabriel Vicente
Author-email: 
License: MIT
